courlan/__init__.py
courlan/clean.py
courlan/cli.py
courlan/core.py
courlan/filters.py
courlan/meta.py
courlan/network.py
courlan/py.typed
courlan/sampling.py
courlan/settings.py
courlan/urlstore.py
courlan/urlutils.py
courlan-1.3.1.dist-info/LICENSE
courlan-1.3.1.dist-info/METADATA
courlan-1.3.1.dist-info/WHEEL
courlan-1.3.1.dist-info/entry_points.txt
courlan-1.3.1.dist-info/top_level.txt
courlan-1.3.1.dist-info/RECORD
