Metadata-Version: 2.1
Name: courlan
Version: 1.3.1
Summary: Clean, filter and sample URLs to optimize data collection – includes spam, content type and language filters.
Author-email: Adrien Barbaresi <barbaresi@bbaw.de>
License: Apache 2.0
Project-URL: Homepage, https://github.com/adbar/courlan
Project-URL: Blog, https://adrien.barbaresi.eu/blog/
Project-URL: Tracker, https://github.com/adbar/courlan/issues
Keywords: cleaner,crawler,uri,url-parsing,url-manipulation,urls,validation,webcrawling
Classifier: Development Status :: 5 - Production/Stable
Classifier: Environment :: Console
Classifier: Intended Audience :: Developers
Classifier: Intended Audience :: Education
Classifier: Intended Audience :: Information Technology
Classifier: Intended Audience :: Science/Research
Classifier: License :: OSI Approved :: Apache Software License
Classifier: Operating System :: MacOS :: MacOS X
Classifier: Operating System :: Microsoft :: Windows
Classifier: Operating System :: POSIX :: Linux
Classifier: Programming Language :: Python
Classifier: Programming Language :: Python :: 3
Classifier: Programming Language :: Python :: 3.8
Classifier: Programming Language :: Python :: 3.9
Classifier: Programming Language :: Python :: 3.10
Classifier: Programming Language :: Python :: 3.11
Classifier: Programming Language :: Python :: 3.12
Classifier: Programming Language :: Python :: 3.13
Classifier: Topic :: Internet :: WWW/HTTP
Classifier: Topic :: Scientific/Engineering :: Information Analysis
Classifier: Topic :: Security
Classifier: Topic :: Text Processing :: Filters
Classifier: Topic :: Text Processing :: Linguistic
Classifier: Typing :: Typed
Requires-Python: >=3.8
License-File: LICENSE
Requires-Dist: babel>=2.16.0
Requires-Dist: tld>=0.13
Requires-Dist: urllib3<3,>=1.26
Provides-Extra: dev
Requires-Dist: black; extra == "dev"
Requires-Dist: mypy; extra == "dev"
Requires-Dist: pytest; extra == "dev"
Requires-Dist: pytest-cov; extra == "dev"
